{"parent":"header-group.json","context":{"market":"cr"},"sections":{"ts_header_PRqBAf":{"settings":{},"blocks":{"switcher_iF396p":{"settings":{"lang_link_1":"\/en-hr\/pages\/promo","lang_link_faq_1":"\/en-hr\/pages\/faq","lang_link_set_1":"\/en-hr\/pages\/set-up","lang_icon_2":"shopify:\/\/shop_images\/Flag_of_Croatia_svg.webp","lang_label_2":"Hrvatski","lang_label_short_2":"Hr","lang_link_2":"\/hr-hr\/pages\/promo","lang_link_faq_2":"\/en-hr\/pages\/faq","lang_link_set_2":"\/hr-hr\/pages\/set-up"}}}}}}