{"sections":{"main":{"type":"main-page","disabled":true,"settings":{"padding_top":28,"padding_bottom":28}},"1746690348404642ae":{"type":"apps","blocks":{"bixgrow_affiliate_landing_page_7PFMNW":{"type":"shopify:\/\/apps\/bixgrow-affiliate\/blocks\/landing_page\/b4f8e2e0-5ee6-49dd-b333-2e5542feb60a","settings":{"affiliate_signup_url":"https:\/\/alite.cc\/pages\/sign-up-affiliate"}}},"block_order":["bixgrow_affiliate_landing_page_7PFMNW"],"custom_css":[".container-fluid {max-width: 1200px;}",".section-how-it-work {max-width: 1200px; margin: auto;}",".section-footer {background-color: #fff;}",".section-footer {background-color: #fff;}",".custom-html {opacity: 0;}"],"settings":{"include_margins":false}}},"order":["main","1746690348404642ae"]}